hello_world_repo/__init__.py
hello_world_repo/hello.py
hello_world_repo-0.0.2.dist-info/LICENSE
hello_world_repo-0.0.2.dist-info/METADATA
hello_world_repo-0.0.2.dist-info/WHEEL
hello_world_repo-0.0.2.dist-info/top_level.txt
hello_world_repo-0.0.2.dist-info/RECORD
