Metadata-Version: 2.1
Name: hello-world-repo
Version: 0.0.2
Summary: Test deployment on gitlab
Home-page: https://github.com/Destination github org or username/hello_world_repo
Author: trung le
Author-email: duc-trung.le@safrangroup.com
License: BSD
Keywords: hello_world_repo
Platform: UNKNOWN
Classifier: Programming Language :: Python :: 2.7
Classifier: Programming Language :: Python :: 3.6
Classifier: Programming Language :: Python :: 3.7
